MANIFEST.in
README.md
setup.py
charms.docker.egg-info/PKG-INFO
charms.docker.egg-info/SOURCES.txt
charms.docker.egg-info/dependency_links.txt
charms.docker.egg-info/top_level.txt
charms/docker/__init__.py
charms/docker/compose.py
charms/docker/docker.py
charms/docker/dockeropts.py
charms/docker/runner.py
charms/docker/workspace.py