Metadata-Version: 1.1
Name: charms.docker
Version: 0.1.18
Summary: Python wrappers for the docker CLI and configuring the Docker Daemon in Juju Charms
Home-page: http://github.com/juju-solutions/charms.docker
Author: Charles Butler
Author-email: charles.butler@ubuntu.com
License: GPLv3
Keywords: docker juju charm charms
Platform: UNKNOWN
Classifier: Development Status :: 3 - Alpha
